{
  "metadata": {
    "code": "278A0",
    "generated_at": "2025-10-03T15:45:05.775146",
    "version": "2.0",
    "type": "listed_info"
  },
  "stock": {
    "code": "278A0",
    "name": "Ｔｅｒｒａ　Ｄｒｏｎｅ",
    "sector": "電機・精密",
    "market": "グロース",
    "currentPrice": 5060.0,
    "change": -110.0,
    "changePercent": -2.127659574468085,
    "volume": 268400,
    "updated_at": "2025-07-11",
    "listed_info": {
      "Date": "2025-07-11",
      "Code": "278A0",
      "CompanyName": "Ｔｅｒｒａ　Ｄｒｏｎｅ",
      "CompanyNameEnglish": "Terra Drone Corporation",
      "Sector17Code": "9",
      "Sector17CodeName": "電機・精密",
      "Sector33Code": "3750",
      "Sector33CodeName": "精密機器",
      "ScaleCategory": "-",
      "MarketCode": "0113",
      "MarketCodeName": "グロース"
    },
    "metadata": {
      "created_at": "2025-10-03T15:28:08.774765",
      "updated_at": "2025-10-03T15:28:08.774766",
      "data_quality": "jquants_official",
      "source": "listed_info_api",
      "price_data_available": true
    }
  }
}