{
  "metadata": {
    "code": "53370",
    "generated_at": "2025-10-03T15:45:05.919540",
    "version": "2.0",
    "type": "listed_info"
  },
  "stock": {
    "code": "53370",
    "name": "ダントーホールディングス",
    "sector": "建設・資材",
    "market": "スタンダード",
    "currentPrice": 913.0,
    "change": -27.0,
    "changePercent": -2.872340425531915,
    "volume": 31900,
    "updated_at": "2025-07-11",
    "listed_info": {
      "Date": "2025-07-11",
      "Code": "53370",
      "CompanyName": "ダントーホールディングス",
      "CompanyNameEnglish": "DANTO HOLDINGS CORPORATION",
      "Sector17Code": "3",
      "Sector17CodeName": "建設・資材",
      "Sector33Code": "3400",
      "Sector33CodeName": "ガラス･土石製品",
      "ScaleCategory": "-",
      "MarketCode": "0112",
      "MarketCodeName": "スタンダード"
    },
    "metadata": {
      "created_at": "2025-10-03T15:34:55.735786",
      "updated_at": "2025-10-03T15:34:55.735788",
      "data_quality": "jquants_official",
      "source": "listed_info_api",
      "price_data_available": true
    }
  }
}