{
  "metadata": {
    "code": "64080",
    "generated_at": "2025-10-03T15:45:05.977116",
    "version": "2.0",
    "type": "listed_info"
  },
  "stock": {
    "code": "64080",
    "name": "小倉クラッチ",
    "sector": "機械",
    "market": "スタンダード",
    "currentPrice": 3655.0,
    "change": 25.0,
    "changePercent": 0.6887052341597797,
    "volume": 600,
    "updated_at": "2025-07-11",
    "listed_info": {
      "Date": "2025-07-11",
      "Code": "64080",
      "CompanyName": "小倉クラッチ",
      "CompanyNameEnglish": "OGURA CLUTCH CO.,LTD.",
      "Sector17Code": "8",
      "Sector17CodeName": "機械",
      "Sector33Code": "3600",
      "Sector33CodeName": "機械",
      "ScaleCategory": "-",
      "MarketCode": "0112",
      "MarketCodeName": "スタンダード"
    },
    "metadata": {
      "created_at": "2025-10-03T15:37:04.914569",
      "updated_at": "2025-10-03T15:37:04.914571",
      "data_quality": "jquants_official",
      "source": "listed_info_api",
      "price_data_available": true
    }
  }
}