{
  "metadata": {
    "code": "8306",
    "generated_at": "2025-10-02T15:07:44.579299",
    "version": "2.0"
  },
  "stock": {
    "code": "8306",
    "name": "三菱UFJフィナンシャル・グループ",
    "sector": "銀行",
    "current_price": {
      "last_price": 24696.93,
      "change": 53.61999999999898,
      "change_percent": 0.02,
      "updated_at": "2025-10-02"
    },
    "volume": {
      "current_volume": 540021,
      "average_volume": 1152788.0,
      "volume_ratio": 1.18
    },
    "technical_indicators": {
      "sma_5": 25131.1,
      "sma_25": 24865.78,
      "sma_75": 24865.78,
      "rsi": 45.67,
      "macd": 4.44,
      "bollinger_upper": 25363.09,
      "bollinger_lower": 24368.46
    },
    "prediction": {
      "predicted_price": 24190.18,
      "confidence": 0.83,
      "model_used": "SampleModel",
      "prediction_date": "2025-10-02T15:07:44.576739"
    },
    "risk_metrics": {
      "volatility": 0.34,
      "beta": 1.28,
      "sharpe_ratio": 0.9,
      "max_drawdown": -0.067
    },
    "metadata": {
      "created_at": "2025-10-02T15:07:44.576741",
      "updated_at": "2025-10-02T15:07:44.576742",
      "data_quality": "sample",
      "last_trade_date": "2025-10-02"
    }
  }
}