{
  "metadata": {
    "generated_at": "2025-10-07T02:46:32.637007",
    "version": "1.0",
    "data_source": "sample_cache"
  },
  "summary": {
    "total_stocks": 5,
    "gainers": 3,
    "losers": 2,
    "unchanged": 0,
    "market_status": "open",
    "last_updated": "2025-10-07T02:46:32.637012"
  },
  "top_gainers": [
    {
      "code": "7203",
      "name": "トヨタ自動車",
      "change_percent": 1.3813580472670717,
      "last_price": 2461.8250182963666
    },
    {
      "code": "6758",
      "name": "ソニーグループ",
      "change_percent": 0.4593135581329215,
      "last_price": 12290.409145995636
    },
    {
      "code": "9984",
      "name": "ソフトバンクグループ",
      "change_percent": 0.3088504336944813,
      "last_price": 8126.060461359847
    },
    {
      "code": "9432",
      "name": "日本電信電話",
      "change_percent": -1.341032711826644,
      "last_price": 4567.066427428114
    },
    {
      "code": "8306",
      "name": "三菱UFJフィナンシャル・グループ",
      "change_percent": -1.7996137400597623,
      "last_price": 1188.1668379672951
    }
  ],
  "top_losers": [
    {
      "code": "7203",
      "name": "トヨタ自動車",
      "change_percent": 1.3813580472670717,
      "last_price": 2461.8250182963666
    },
    {
      "code": "6758",
      "name": "ソニーグループ",
      "change_percent": 0.4593135581329215,
      "last_price": 12290.409145995636
    },
    {
      "code": "9984",
      "name": "ソフトバンクグループ",
      "change_percent": 0.3088504336944813,
      "last_price": 8126.060461359847
    },
    {
      "code": "9432",
      "name": "日本電信電話",
      "change_percent": -1.341032711826644,
      "last_price": 4567.066427428114
    },
    {
      "code": "8306",
      "name": "三菱UFJフィナンシャル・グループ",
      "change_percent": -1.7996137400597623,
      "last_price": 1188.1668379672951
    }
  ]
}