{
  "metadata": {
    "generated_at": "2025-10-06T02:35:09.249772",
    "version": "1.0"
  },
  "metrics": {
    "overall": {
      "accuracy": 0.839,
      "precision": 0.838,
      "recall": 0.801,
      "f1_score": 0.812
    },
    "regression": {
      "mae": 0.165,
      "rmse": 0.213,
      "r2": 0.763,
      "mape": 0.189
    },
    "classification": {
      "accuracy": 0.873,
      "precision": 0.824,
      "recall": 0.889,
      "f1_score": 0.865
    }
  },
  "evaluation_date": "2025-10-06T02:35:09.249776"
}