{
  "metadata": {
    "generated_at": "2025-10-04T22:10:44.083339",
    "version": "1.0",
    "total_predictions": 5
  },
  "predictions": [
    {
      "code": "7203",
      "name": "トヨタ自動車",
      "current_price": 2566.0973650071664,
      "predicted_price": 2566.116569254935,
      "confidence": 0.796094682193657,
      "change_percent": 2.0,
      "model_used": "Random Forest",
      "prediction_date": "2025-10-04T22:10:44.082989"
    },
    {
      "code": "6758",
      "name": "ソニーグループ",
      "current_price": 11568.92686753042,
      "predicted_price": 11584.266947221062,
      "confidence": 0.7994812545521603,
      "change_percent": 2.0,
      "model_used": "XGBoost",
      "prediction_date": "2025-10-04T22:10:44.083002"
    },
    {
      "code": "9984",
      "name": "ソフトバンクグループ",
      "current_price": 7941.728857613274,
      "predicted_price": 8213.844125605381,
      "confidence": 0.8275776366206242,
      "change_percent": 2.0,
      "model_used": "Linear Regression",
      "prediction_date": "2025-10-04T22:10:44.083013"
    },
    {
      "code": "9432",
      "name": "日本電信電話",
      "current_price": 4451.805081448357,
      "predicted_price": 4632.440173231431,
      "confidence": 0.7595476306431629,
      "change_percent": 2.0,
      "model_used": "Random Forest",
      "prediction_date": "2025-10-04T22:10:44.083029"
    },
    {
      "code": "8306",
      "name": "三菱UFJフィナンシャル・グループ",
      "current_price": 1246.8439140266912,
      "predicted_price": 1235.771725870692,
      "confidence": 0.7929446049695369,
      "change_percent": 2.0,
      "model_used": "XGBoost",
      "prediction_date": "2025-10-04T22:10:44.083042"
    }
  ]
}