{
  "dates": [
    "2024-01-01",
    "2024-01-02",
    "2024-01-03",
    "2024-01-04",
    "2024-01-05",
    "2024-01-08",
    "2024-01-09",
    "2024-01-10",
    "2024-01-11",
    "2024-01-12",
    "2024-01-15"
  ],
  "risk_scores": [
    5.2,
    5.8,
    6.1,
    5.9,
    6.3,
    6.5,
    6.2,
    6.0,
    6.4,
    6.7,
    6.5
  ],
  "portfolio_values": [
    1000000,
    1005000,
    1012000,
    1008000,
    1015000,
    1020000,
    1018000,
    1022000,
    1019000,
    1025000,
    1050000
  ],
  "drawdowns": [
    0,
    -0.5,
    -1.2,
    -0.8,
    -1.5,
    -2.0,
    -1.8,
    -2.2,
    -1.9,
    -2.5,
    -2.2
  ],
  "current_risk_score": 6.5,
  "current_portfolio_value": 1050000,
  "current_drawdown": -2.2
}
